setup.py
arkdbtools/__init__.py
arkdbtools/config.py
arkdbtools/dbtools.py
arkdbtools/utils.py
arkdbtools.egg-info/PKG-INFO
arkdbtools.egg-info/SOURCES.txt
arkdbtools.egg-info/dependency_links.txt
arkdbtools.egg-info/top_level.txt
arkdbtools/tests/__init__.py
arkdbtools/tests/test_address.py
arkdbtools/tests/test_blockchain.py
arkdbtools/tests/test_core.py
arkdbtools/tests/test_delegate.py
arkdbtools/tests/test_delegate_share.py
arkdbtools/tests/test_delegate_trueshare.py
arkdbtools/tests/test_get_transactionlist.py
arkdbtools/tests/test_node.py
arkdbtools/tests/test_set_calculation.py
arkdbtools/tests/test_set_connection.py
arkdbtools/tests/test_set_delegate.py
arkdbtools/tests/test_set_sender.py