Metadata-Version: 1.0
Name: arkdbtools
Version: 0.2.18
Summary: toolkit for dealing with the ark blockchain
Home-page: https://github.com/BlockHub/arkdbtools
Author: karel
Author-email: karel@blockhub.nl
License: MIT
Platform: UNKNOWN
